{
  "sets": [
    {
      "file": "ECO0019_P1.json",
      "code": "ECO0019",
      "title": "Introdução à Economia - Prova 1",
      "subject": "Economia",
      "group": "Prova 1"
    },
    {
      "file": "ECO0019_P2.json",
      "code": "ECO0019",
      "title": "Introdução à Economia - Prova 2",
      "subject": "Economia",
      "group": "Prova 2"
    },
    {
      "file": "PPCA0021_S2.json",
      "code": "PPCA0021_S2",
      "title": "MTDeGD - Texto 2",
      "subject": "Metodologia Científica",
      "group": "Teste 2"
    }
  ]
}
